{
  "label": "SDM26",
  "junction_type": "characteristic",
  "points": [
    {
      "cycle": 11,
      "mass_total": 0.0038033409767071367,
      "mass_drift": -4.283204018720602e-05,
      "mass_in_restrictor": 0.0006161862175420918,
      "mass_out_collector": 0.0006590680981982856,
      "net_port_flow": -4.288188065619384e-05,
      "nonconservation": 4.984046898782145e-08,
      "imep_bar": 12.326531778447729,
      "bmep_bar": 9.720281778447728,
      "fmep_bar": 2.60625,
      "ve_atm": 0.8742151373661837,
      "intake_mass_per_cycle_g": 0.616623669375285,
      "indicated_power_kW": 36.9402059297626,
      "indicated_power_hp": 49.53762361507656,
      "brake_power_kW": 29.129784195988613,
      "brake_power_hp": 39.06367734476145,
      "wheel_power_kW": 26.50810361834964,
      "wheel_power_hp": 35.54794638373292,
      "indicated_torque_Nm": 58.79216372554261,
      "brake_torque_Nm": 46.3614914599176,
      "wheel_torque_Nm": 42.18895722852502,
      "EGT_mean": 966.500195540036,
      "rpm": 6000.0,
      "converged_cycle": 10,
      "n_cycles_run": 11,
      "step_count": 25215,
      "wall_time_s": 17.09066104888916,
      "nonconservation_max": 4.984046898782145e-08,
      "raw_drift_final": -4.283204018720602e-05,
      "regime_counts": {
        "startup": 6629,
        "subsonic_inflow": 1738,
        "choked_inflow": 28576,
        "subsonic_outflow": 24356,
        "choked_outflow": 449
      }
    },
    {
      "cycle": 11,
      "mass_total": 0.0037507112448834337,
      "mass_drift": -4.4735740030620724e-05,
      "mass_in_restrictor": 0.0005653708603194147,
      "mass_out_collector": 0.000610106600350052,
      "net_port_flow": -4.473574003063731e-05,
      "nonconservation": 1.6588293239028218e-17,
      "imep_bar": 11.607833963138162,
      "bmep_bar": 8.832616949249275,
      "fmep_bar": 2.775217013888889,
      "ve_atm": 0.8010044818527456,
      "intake_mass_per_cycle_g": 0.5649848666246563,
      "indicated_power_kW": 37.68527650457371,
      "indicated_power_hp": 50.53677954213988,
      "brake_power_kW": 28.675428426050214,
      "brake_power_hp": 38.45437632566744,
      "wheel_power_kW": 26.0946398677057,
      "wheel_power_hp": 34.99348245635738,
      "indicated_torque_Nm": 55.36428957681018,
      "brake_torque_Nm": 42.12771857800375,
      "wheel_torque_Nm": 38.33622390598342,
      "EGT_mean": 1035.9986801305608,
      "rpm": 6500.0,
      "converged_cycle": 10,
      "n_cycles_run": 11,
      "step_count": 23533,
      "wall_time_s": 15.87323784828186,
      "nonconservation_max": 4.2825985813177425e-17,
      "raw_drift_final": -4.4735740030620724e-05,
      "regime_counts": {
        "startup": 6272,
        "subsonic_inflow": 1828,
        "choked_inflow": 28735,
        "subsonic_outflow": 20672,
        "choked_outflow": 132
      }
    },
    {
      "cycle": 12,
      "mass_total": 0.0037229322037029555,
      "mass_drift": -3.084288580386353e-05,
      "mass_in_restrictor": 0.0006640171476856195,
      "mass_out_collector": 0.0006948815522097304,
      "net_port_flow": -3.0864404524110845e-05,
      "nonconservation": 2.1518720247316533e-08,
      "imep_bar": 13.63500817037186,
      "bmep_bar": 10.685806781482972,
      "fmep_bar": 2.9492013888888886,
      "ve_atm": 0.9431442210313751,
      "intake_mass_per_cycle_g": 0.6652424849043312,
      "indicated_power_kW": 47.6716961840708,
      "indicated_power_hp": 63.92878662206087,
      "brake_power_kW": 37.360486184046536,
      "brake_power_hp": 50.101228622832956,
      "wheel_power_kW": 33.99804242748235,
      "wheel_power_hp": 45.592118046778,
      "indicated_torque_Nm": 65.03302365659925,
      "brake_torque_Nm": 50.96662330720688,
      "wheel_torque_Nm": 46.379627209558265,
      "EGT_mean": 1035.7923886877084,
      "rpm": 7000.0,
      "converged_cycle": 11,
      "n_cycles_run": 12,
      "step_count": 24843,
      "wall_time_s": 16.845723867416382,
      "nonconservation_max": 2.1518720247316533e-08,
      "raw_drift_final": -3.084288580386353e-05,
      "regime_counts": {
        "startup": 5829,
        "subsonic_inflow": 1471,
        "choked_inflow": 30477,
        "subsonic_outflow": 22090,
        "choked_outflow": 921
      }
    },
    {
      "cycle": 11,
      "mass_total": 0.0037314164010498695,
      "mass_drift": -3.1847283244448073e-05,
      "mass_in_restrictor": 0.0006469368192420998,
      "mass_out_collector": 0.0006787301017328276,
      "net_port_flow": -3.179328249072776e-05,
      "nonconservation": -5.400075372031122e-08,
      "imep_bar": 13.486480632079292,
      "bmep_bar": 10.358277507079295,
      "fmep_bar": 3.1282031249999998,
      "ve_atm": 0.919121812035996,
      "intake_mass_per_cycle_g": 0.6482983880237944,
      "indicated_power_kW": 50.52043234576208,
      "indicated_power_hp": 67.74900408443352,
      "brake_power_kW": 38.80216583489413,
      "brake_power_hp": 52.034552547799564,
      "wheel_power_kW": 35.30997090975366,
      "wheel_power_hp": 47.351442818497596,
      "indicated_torque_Nm": 64.3246122797417,
      "brake_torque_Nm": 49.40445196235889,
      "wheel_torque_Nm": 44.95805128574659,
      "EGT_mean": 985.454535132021,
      "rpm": 7500.0,
      "converged_cycle": 10,
      "n_cycles_run": 11,
      "step_count": 21499,
      "wall_time_s": 14.570235013961792,
      "nonconservation_max": 5.400075372031122e-08,
      "raw_drift_final": -3.1847283244448073e-05,
      "regime_counts": {
        "startup": 5321,
        "subsonic_inflow": 1366,
        "choked_inflow": 27330,
        "subsonic_outflow": 18438,
        "choked_outflow": 222
      }
    },
    {
      "cycle": 11,
      "mass_total": 0.00367335652681026,
      "mass_drift": -4.6287380496585085e-05,
      "mass_in_restrictor": 0.0007204790798174455,
      "mass_out_collector": 0.000765868414561013,
      "net_port_flow": -4.5389334743567455e-05,
      "nonconservation": -8.980457530176301e-07,
      "imep_bar": 15.089648350272725,
      "bmep_bar": 11.777426128050505,
      "fmep_bar": 3.312222222222222,
      "ve_atm": 1.0270981171042453,
      "intake_mass_per_cycle_g": 0.7244589835007408,
      "indicated_power_kW": 60.29430148296174,
      "indicated_power_hp": 80.85597624106443,
      "brake_power_kW": 47.05952485931546,
      "brake_power_hp": 63.10785149432139,
      "wheel_power_kW": 42.824167621977075,
      "wheel_power_hp": 57.42814485983247,
      "indicated_torque_Nm": 71.97102090964769,
      "brake_torque_Nm": 56.1731700068699,
      "wheel_torque_Nm": 51.11758470625161,
      "EGT_mean": 1024.5145548438586,
      "rpm": 8000.0,
      "converged_cycle": 10,
      "n_cycles_run": 11,
      "step_count": 20764,
      "wall_time_s": 14.28752589225769,
      "nonconservation_max": 8.980457530176301e-07,
      "raw_drift_final": -4.6287380496585085e-05,
      "regime_counts": {
        "startup": 4610,
        "subsonic_inflow": 1150,
        "choked_inflow": 24458,
        "subsonic_outflow": 19965,
        "choked_outflow": 825
      }
    },
    {
      "cycle": 13,
      "mass_total": 0.003596324330499213,
      "mass_drift": -2.059795987725821e-05,
      "mass_in_restrictor": 0.0006756761679356345,
      "mass_out_collector": 0.0006961295177342366,
      "net_port_flow": -2.0453349798602114e-05,
      "nonconservation": -1.446100786560954e-07,
      "imep_bar": 14.413436649364808,
      "bmep_bar": 10.912177968809251,
      "fmep_bar": 3.5012586805555554,
      "ve_atm": 0.9605618254932367,
      "intake_mass_per_cycle_g": 0.6775279129596702,
      "indicated_power_kW": 61.19185677690634,
      "indicated_power_hp": 82.0596175095968,
      "brake_power_kW": 46.3273574259554,
      "brake_power_hp": 62.12599896198927,
      "wheel_power_kW": 42.157895257619415,
      "wheel_power_hp": 56.53465905541023,
      "indicated_torque_Nm": 68.74578693893605,
      "brake_torque_Nm": 52.04631483335878,
      "wheel_torque_Nm": 47.36214649835649,
      "EGT_mean": 1042.6312821839174,
      "rpm": 8500.0,
      "converged_cycle": 12,
      "n_cycles_run": 13,
      "step_count": 23406,
      "wall_time_s": 16.061207056045532,
      "nonconservation_max": 7.835178936903579e-07,
      "raw_drift_final": -2.059795987725821e-05,
      "regime_counts": {
        "startup": 5199,
        "subsonic_inflow": 1113,
        "choked_inflow": 28045,
        "subsonic_outflow": 22567,
        "choked_outflow": 645
      }
    },
    {
      "cycle": 13,
      "mass_total": 0.0035750509190667096,
      "mass_drift": -4.2837905743716136e-05,
      "mass_in_restrictor": 0.0006635523854315187,
      "mass_out_collector": 0.0007062056864533807,
      "net_port_flow": -4.265330102186198e-05,
      "nonconservation": -1.8460472185415858e-07,
      "imep_bar": 14.331280242924521,
      "bmep_bar": 10.635967742924521,
      "fmep_bar": 3.6953125,
      "ve_atm": 0.9467081058670916,
      "intake_mass_per_cycle_g": 0.6677562548571729,
      "indicated_power_kW": 64.42206773072996,
      "indicated_power_hp": 86.39140100674528,
      "brake_power_kW": 47.81087402535634,
      "brake_power_hp": 64.11542714946539,
      "wheel_power_kW": 43.507895363074276,
      "wheel_power_hp": 58.34503870601351,
      "indicated_torque_Nm": 68.35393682364369,
      "brake_torque_Nm": 50.728912897862436,
      "wheel_torque_Nm": 46.16331073705482,
      "EGT_mean": 1131.402879294693,
      "rpm": 9000.0,
      "converged_cycle": 12,
      "n_cycles_run": 13,
      "step_count": 21993,
      "wall_time_s": 15.269199132919312,
      "nonconservation_max": 2.3947762805350426e-07,
      "raw_drift_final": -4.2837905743716136e-05,
      "regime_counts": {
        "startup": 5093,
        "subsonic_inflow": 1412,
        "choked_inflow": 26825,
        "subsonic_outflow": 20776,
        "choked_outflow": 106
      }
    },
    {
      "cycle": 15,
      "mass_total": 0.003470322950288114,
      "mass_drift": -2.9262912659859096e-05,
      "mass_in_restrictor": 0.000618017895476551,
      "mass_out_collector": 0.0006474438538287747,
      "net_port_flow": -2.9425958352223666e-05,
      "nonconservation": 1.6304569236456987e-07,
      "imep_bar": 13.552652903906663,
      "bmep_bar": 9.658269223351105,
      "fmep_bar": 3.8943836805555563,
      "ve_atm": 0.8799500344662816,
      "intake_mass_per_cycle_g": 0.6206687529504861,
      "indicated_power_kW": 64.30653112800593,
      "indicated_power_hp": 86.23646389701746,
      "brake_power_kW": 45.827912428499914,
      "brake_power_hp": 61.45623230320492,
      "wheel_power_kW": 41.70340030993492,
      "wheel_power_hp": 55.92517139591648,
      "indicated_torque_Nm": 64.64022506598934,
      "brake_torque_Nm": 46.06571870259958,
      "wheel_torque_Nm": 41.91980401936562,
      "EGT_mean": 1125.3674979288646,
      "rpm": 9500.0,
      "converged_cycle": 14,
      "n_cycles_run": 15,
      "step_count": 24401,
      "wall_time_s": 16.853989124298096,
      "nonconservation_max": 4.825396264575591e-07,
      "raw_drift_final": -2.9262912659859096e-05,
      "regime_counts": {
        "startup": 7070,
        "subsonic_inflow": 2033,
        "choked_inflow": 27411,
        "subsonic_outflow": 23188,
        "choked_outflow": 100
      }
    },
    {
      "cycle": 15,
      "mass_total": 0.003443338240548654,
      "mass_drift": -3.228213187714615e-05,
      "mass_in_restrictor": 0.0005958574739916334,
      "mass_out_collector": 0.0006280686950564313,
      "net_port_flow": -3.221122106479796e-05,
      "nonconservation": -7.09108123481952e-08,
      "imep_bar": 13.307882981030208,
      "bmep_bar": 9.209410758807985,
      "fmep_bar": 4.098472222222222,
      "ve_atm": 0.8474665274631318,
      "intake_mass_per_cycle_g": 0.5977566590890068,
      "indicated_power_kW": 66.46853938644873,
      "indicated_power_hp": 89.13576423018469,
      "brake_power_kW": 45.99800604050892,
      "brake_power_hp": 61.6843315549268,
      "wheel_power_kW": 41.858185496863115,
      "wheel_power_hp": 56.13274171498339,
      "indicated_torque_Nm": 63.47277962070991,
      "brake_torque_Nm": 43.92486020230713,
      "wheel_torque_Nm": 39.97162278409949,
      "EGT_mean": 1073.3239744204704,
      "rpm": 10000.0,
      "converged_cycle": 14,
      "n_cycles_run": 15,
      "step_count": 23250,
      "wall_time_s": 16.202611923217773,
      "nonconservation_max": 6.297735530234319e-07,
      "raw_drift_final": -3.228213187714615e-05,
      "regime_counts": {
        "startup": 8084,
        "subsonic_inflow": 1833,
        "choked_inflow": 25472,
        "subsonic_outflow": 21115,
        "choked_outflow": 97
      }
    },
    {
      "cycle": 19,
      "mass_total": 0.003354546582428189,
      "mass_drift": -1.1634818240403334e-05,
      "mass_in_restrictor": 0.0006157493749542965,
      "mass_out_collector": 0.0006277737865232576,
      "net_port_flow": -1.2024411568961114e-05,
      "nonconservation": 3.8959332855777965e-07,
      "imep_bar": 13.932858837205137,
      "bmep_bar": 9.625280712205136,
      "fmep_bar": 4.307578125,
      "ve_atm": 0.8793707892913357,
      "intake_mass_per_cycle_g": 0.6202601850019612,
      "indicated_power_kW": 73.06959465995041,
      "indicated_power_hp": 97.98792364214886,
      "brake_power_kW": 50.478898002683685,
      "brake_power_hp": 67.69330562248047,
      "wheel_power_kW": 45.93579718244216,
      "wheel_power_hp": 61.60090811645723,
      "indicated_torque_Nm": 66.45364102772724,
      "brake_torque_Nm": 45.90837793690693,
      "wheel_torque_Nm": 41.77662392258531,
      "EGT_mean": 1103.465585462396,
      "rpm": 10500.0,
      "converged_cycle": 18,
      "n_cycles_run": 19,
      "step_count": 29591,
      "wall_time_s": 20.26733708381653,
      "nonconservation_max": 8.26980067696265e-07,
      "raw_drift_final": -1.1634818240403334e-05,
      "regime_counts": {
        "startup": 9855,
        "subsonic_inflow": 2189,
        "choked_inflow": 34077,
        "subsonic_outflow": 25667,
        "choked_outflow": 94
      }
    },
    {
      "cycle": 18,
      "mass_total": 0.003320562834967269,
      "mass_drift": -1.584203278017903e-05,
      "mass_in_restrictor": 0.0006214826396607935,
      "mass_out_collector": 0.0006374486661205935,
      "net_port_flow": -1.5966026459799916e-05,
      "nonconservation": 1.2399367962088494e-07,
      "imep_bar": 14.004997184293305,
      "bmep_bar": 9.483295795404416,
      "fmep_bar": 4.521701388888889,
      "ve_atm": 0.8903750930842863,
      "intake_mass_per_cycle_g": 0.6280220206116406,
      "indicated_power_kW": 76.9454374603438,
      "indicated_power_hp": 103.18551355819201,
      "brake_power_kW": 52.10256981426536,
      "brake_power_hp": 69.87068501309555,
      "wheel_power_kW": 47.41333853098148,
      "wheel_power_hp": 63.582323361916956,
      "indicated_torque_Nm": 66.79770938281096,
      "brake_torque_Nm": 45.23117200216859,
      "wheel_torque_Nm": 41.16036652197342,
      "EGT_mean": 1133.4797184569043,
      "rpm": 11000.0,
      "converged_cycle": 17,
      "n_cycles_run": 18,
      "step_count": 27224,
      "wall_time_s": 18.818884134292603,
      "nonconservation_max": 9.384893701330907e-07,
      "raw_drift_final": -1.584203278017903e-05,
      "regime_counts": {
        "startup": 5906,
        "subsonic_inflow": 1790,
        "choked_inflow": 33762,
        "subsonic_outflow": 24660,
        "choked_outflow": 91
      }
    },
    {
      "cycle": 17,
      "mass_total": 0.0032613169231108345,
      "mass_drift": -2.1962881075767403e-05,
      "mass_in_restrictor": 0.0006277412303242466,
      "mass_out_collector": 0.0006498900930634238,
      "net_port_flow": -2.2148862739177237e-05,
      "nonconservation": 1.85981663409834e-07,
      "imep_bar": 14.108909820521239,
      "bmep_bar": 9.368067806632348,
      "fmep_bar": 4.740842013888889,
      "ve_atm": 0.9046118303327025,
      "intake_mass_per_cycle_g": 0.6380638384512384,
      "indicated_power_kW": 81.03981856905813,
      "indicated_power_hp": 108.67616812264734,
      "brake_power_kW": 53.8090132440915,
      "brake_power_hp": 72.15906295305284,
      "wheel_power_kW": 48.96620205212327,
      "wheel_power_hp": 65.66474728727809,
      "indicated_torque_Nm": 67.29332719583984,
      "brake_torque_Nm": 44.681584907970915,
      "wheel_torque_Nm": 40.66024226625353,
      "EGT_mean": 1163.081415446863,
      "rpm": 11500.0,
      "converged_cycle": 16,
      "n_cycles_run": 17,
      "step_count": 25028,
      "wall_time_s": 17.1771183013916,
      "nonconservation_max": 5.88619964133133e-07,
      "raw_drift_final": -2.1962881075767403e-05,
      "regime_counts": {
        "startup": 6375,
        "subsonic_inflow": 1569,
        "choked_inflow": 31306,
        "subsonic_outflow": 21669,
        "choked_outflow": 90
      }
    },
    {
      "cycle": 19,
      "mass_total": 0.003224729420315378,
      "mass_drift": -4.933913106511777e-06,
      "mass_in_restrictor": 0.0005969573916891561,
      "mass_out_collector": 0.0006024635286480551,
      "net_port_flow": -5.50613695889904e-06,
      "nonconservation": 5.722238523872634e-07,
      "imep_bar": 12.980890340596044,
      "bmep_bar": 8.015890340596043,
      "fmep_bar": 4.965000000000002,
      "ve_atm": 0.8472491242058106,
      "intake_mass_per_cycle_g": 0.5976033146906617,
      "indicated_power_kW": 77.802381229681,
      "indicated_power_hp": 104.33469388451255,
      "brake_power_kW": 48.04411252315798,
      "brake_power_hp": 64.42820507329755,
      "wheel_power_kW": 43.72014239607376,
      "wheel_power_hp": 58.62966661670076,
      "indicated_torque_Nm": 61.91316778511913,
      "brake_torque_Nm": 38.23228997261912,
      "wheel_torque_Nm": 34.791383875083405,
      "EGT_mean": 1177.7432451880552,
      "rpm": 12000.0,
      "converged_cycle": 18,
      "n_cycles_run": 19,
      "step_count": 27777,
      "wall_time_s": 19.240187883377075,
      "nonconservation_max": 5.722238523872634e-07,
      "raw_drift_final": -4.933913106511777e-06,
      "regime_counts": {
        "startup": 8906,
        "subsonic_inflow": 1557,
        "choked_inflow": 33857,
        "subsonic_outflow": 23195,
        "choked_outflow": 271
      }
    },
    {
      "cycle": 17,
      "mass_total": 0.0032792422266163354,
      "mass_drift": -1.582138450405713e-05,
      "mass_in_restrictor": 0.0005303860589484773,
      "mass_out_collector": 0.0005462509283552851,
      "net_port_flow": -1.5864869406807813e-05,
      "nonconservation": 4.348490275068312e-08,
      "imep_bar": 11.563624495672281,
      "bmep_bar": 6.369449148450059,
      "fmep_bar": 5.194175347222222,
      "ve_atm": 0.7544708094428901,
      "intake_mass_per_cycle_g": 0.5321625525232092,
      "indicated_power_kW": 72.19567072917663,
      "indicated_power_hp": 96.81597254817838,
      "brake_power_kW": 39.76665392583734,
      "brake_power_hp": 53.327952160168074,
      "wheel_power_kW": 36.18765507251198,
      "wheel_power_hp": 48.528436465752954,
      "indicated_torque_Nm": 55.15342975863994,
      "brake_torque_Nm": 30.379485804104345,
      "wheel_torque_Nm": 27.645332081734956,
      "EGT_mean": 1211.2072852126912,
      "rpm": 12500.0,
      "converged_cycle": 16,
      "n_cycles_run": 17,
      "step_count": 23299,
      "wall_time_s": 16.256736040115356,
      "nonconservation_max": 1.2063021786830243e-06,
      "raw_drift_final": -1.582138450405713e-05,
      "regime_counts": {
        "startup": 7566,
        "subsonic_inflow": 1298,
        "choked_inflow": 27263,
        "subsonic_outflow": 17761,
        "choked_outflow": 3159
      }
    },
    {
      "cycle": 17,
      "mass_total": 0.003310842938371647,
      "mass_drift": -1.4702473794878882e-05,
      "mass_in_restrictor": 0.00046543844957970553,
      "mass_out_collector": 0.0004802252728912914,
      "net_port_flow": -1.4786823311585876e-05,
      "nonconservation": 8.434951670699365e-08,
      "imep_bar": 10.155443749994575,
      "bmep_bar": 4.72707569443902,
      "fmep_bar": 5.428368055555556,
      "ve_atm": 0.6600921714705157,
      "intake_mass_per_cycle_g": 0.46559300966159844,
      "indicated_power_kW": 65.9400723615666,
      "indicated_power_hp": 88.4270783982387,
      "brake_power_kW": 30.69326373355947,
      "brake_power_hp": 41.160337580205805,
      "wheel_power_kW": 27.930869997539116,
      "wheel_power_hp": 37.45590719798728,
      "indicated_torque_Nm": 48.43702368083351,
      "brake_torque_Nm": 22.54608296685781,
      "wheel_torque_Nm": 20.516935499840606,
      "EGT_mean": 1237.6635511679438,
      "rpm": 13000.0,
      "converged_cycle": 16,
      "n_cycles_run": 17,
      "step_count": 22127,
      "wall_time_s": 15.323801040649414,
      "nonconservation_max": 1.2423165201621168e-06,
      "raw_drift_final": -1.4702473794878882e-05,
      "regime_counts": {
        "startup": 7447,
        "subsonic_inflow": 1162,
        "choked_inflow": 25496,
        "subsonic_outflow": 15442,
        "choked_outflow": 4746
      }
    },
    {
      "cycle": 18,
      "mass_total": 0.0033281502419801544,
      "mass_drift": -1.6070999815864188e-05,
      "mass_in_restrictor": 0.00040193223280368906,
      "mass_out_collector": 0.00041786961225011076,
      "net_port_flow": -1.5937379446421705e-05,
      "nonconservation": -1.3362036944248278e-07,
      "imep_bar": 8.912421395799145,
      "bmep_bar": 3.2448432707991453,
      "fmep_bar": 5.667578125,
      "ve_atm": 0.5712285920599173,
      "intake_mass_per_cycle_g": 0.40291348826247064,
      "indicated_power_kW": 60.094765269325364,
      "indicated_power_hp": 80.58839381698452,
      "brake_power_kW": 21.8793620762071,
      "brake_power_hp": 29.34070279764932,
      "wheel_power_kW": 19.910219489348464,
      "wheel_power_hp": 26.700039545860886,
      "indicated_torque_Nm": 42.50835087360127,
      "brake_torque_Nm": 15.476482782780952,
      "wheel_torque_Nm": 14.083599332330667,
      "EGT_mean": 1255.0442390505068,
      "rpm": 13500.0,
      "converged_cycle": 17,
      "n_cycles_run": 18,
      "step_count": 22180,
      "wall_time_s": 15.359451055526733,
      "nonconservation_max": 1.1268453876762063e-06,
      "raw_drift_final": -1.6070999815864188e-05,
      "regime_counts": {
        "startup": 7963,
        "subsonic_inflow": 1449,
        "choked_inflow": 24669,
        "subsonic_outflow": 16461,
        "choked_outflow": 4056
      }
    }
  ],
  "total_wall_s": 265.6000130176544,
  "regime_total": {
    "startup": 108125,
    "subsonic_inflow": 24958,
    "choked_inflow": 457759,
    "subsonic_outflow": 338022,
    "choked_outflow": 16004
  }
}